flowdapt/__init__.py
flowdapt/__main__.py
flowdapt/py.typed
flowdapt/builtins/__init__.py
flowdapt/builtins/utils.py
flowdapt/cli/__init__.py
flowdapt/cli/_internal.py
flowdapt/cli/config.py
flowdapt/cli/db.py
flowdapt/cli/dev.py
flowdapt/cli/main.py
flowdapt/cli/run.py
flowdapt/cli/utils.py
flowdapt/compute/__init__.py
flowdapt/compute/object_store.py
flowdapt/compute/service.py
flowdapt/compute/utils.py
flowdapt/compute/artifacts/__init__.py
flowdapt/compute/artifacts/interface.py
flowdapt/compute/artifacts/misc.py
flowdapt/compute/artifacts/dataset/__init__.py
flowdapt/compute/artifacts/dataset/arrays.py
flowdapt/compute/artifacts/dataset/dataframes.py
flowdapt/compute/artifacts/dataset/handler.py
flowdapt/compute/artifacts/dataset/utils.py
flowdapt/compute/cluster_memory/__init__.py
flowdapt/compute/cluster_memory/base.py
flowdapt/compute/cluster_memory/utils.py
flowdapt/compute/domain/__init__.py
flowdapt/compute/domain/dto/__init__.py
flowdapt/compute/domain/dto/v1/__init__.py
flowdapt/compute/domain/dto/v1/config.py
flowdapt/compute/domain/dto/v1/workflow.py
flowdapt/compute/domain/dto/v1/workflowrun.py
flowdapt/compute/domain/events/__init__.py
flowdapt/compute/domain/events/workflow.py
flowdapt/compute/domain/models/__init__.py
flowdapt/compute/domain/models/config.py
flowdapt/compute/domain/models/workflow.py
flowdapt/compute/domain/models/workflowrun.py
flowdapt/compute/executor/__init__.py
flowdapt/compute/executor/base.py
flowdapt/compute/executor/dask/__init__.py
flowdapt/compute/executor/dask/cluster_memory.py
flowdapt/compute/executor/dask/collections.py
flowdapt/compute/executor/dask/executor.py
flowdapt/compute/executor/dask/gpu_cluster.py
flowdapt/compute/executor/dask/plugins.py
flowdapt/compute/executor/local/__init__.py
flowdapt/compute/executor/local/cluster_memory.py
flowdapt/compute/executor/local/executor.py
flowdapt/compute/executor/ray/__init__.py
flowdapt/compute/executor/ray/cluster_memory.py
flowdapt/compute/executor/ray/executor.py
flowdapt-0.1.37.dist-info/METADATA
flowdapt-0.1.37.dist-info/WHEEL
flowdapt-0.1.37.dist-info/entry_points.txt
flowdapt-0.1.37.dist-info/licenses/LICENSE
flowdapt-0.1.37.dist-info/RECORD
