Metadata-Version: 2.4
Name: flowdapt
Version: 0.1.37
Summary: A generalized framework for robust modular deployments of large-scale, real-time adaptive modeling on chaotic data.
Author-email: "Emergent Methods, LLC" <contact@emergentmethods.ai>
License: Apache-2.0
License-File: LICENSE
Classifier: Programming Language :: Python
Classifier: Programming Language :: Python :: 3.11
Classifier: Programming Language :: Python :: 3.12
Requires-Python: >=3.11
Requires-Dist: aiosonic>=0.27.0
Requires-Dist: aiotinydb>=2.0.0
Requires-Dist: anyio>=4.11.0
Requires-Dist: async-timeout>=4.0.3
Requires-Dist: asyncer>=0.0.9
Requires-Dist: asynctempfile>=0.5.0
Requires-Dist: cloudpickle==3.1.1
Requires-Dist: coolname>=2.2.0
Requires-Dist: crontab>=1.0.5
Requires-Dist: cryptography>=40.0.2
Requires-Dist: dask[dataframe,diagnostics,distributed]==2025.2.0
Requires-Dist: dill>=0.4.0
Requires-Dist: fastapi>=0.119.0
Requires-Dist: gpustat==1.1.1
Requires-Dist: llvmlite>=0.43.0
Requires-Dist: motor>=3.3.1
Requires-Dist: numpy<3.0.0,>=1.26.4
Requires-Dist: nvidia-ml-py>=13.580.82
Requires-Dist: opentelemetry-api>=1.30.0
Requires-Dist: opentelemetry-exporter-otlp-proto-http>=1.30.0
Requires-Dist: opentelemetry-exporter-otlp>=1.30.0
Requires-Dist: opentelemetry-instrumentation-asgi>=0.51b0
Requires-Dist: opentelemetry-instrumentation-sqlalchemy>=0.51b0
Requires-Dist: opentelemetry-instrumentation-system-metrics>=0.51b0
Requires-Dist: opentelemetry-sdk>=1.30.0
Requires-Dist: orjson>=3.10.15
Requires-Dist: pandas>=2.0.2
Requires-Dist: pyarrow>=15.0.0
Requires-Dist: pydantic<2.12.0,>=2.5.3
Requires-Dist: pympler>=1.0.1
Requires-Dist: python-dotenv>=1.0.0
Requires-Dist: python-manifest>=2.2.3
Requires-Dist: python-multipart>=0.0.6
Requires-Dist: python-rapidjson>=1.21
Requires-Dist: pytimeparse>=1.1.8
Requires-Dist: ray[default]==2.43.0
Requires-Dist: rich>=14.2.0
Requires-Dist: s3fs>=2023.12.1
Requires-Dist: semver>=3.0.4
Requires-Dist: structlog>=23.1.0
Requires-Dist: tinydb-serialization>=2.1.1
Requires-Dist: tinydb>=4.8.0
Requires-Dist: typer>=0.19.2
Requires-Dist: uvicorn>=0.37.0
Requires-Dist: uvloop>=0.21.0
